sqlalchemy_pyodbc_mssql/__init__.py
sqlalchemy_pyodbc_mssql/dialect.py
sqlalchemy_pyodbc_mssql/version.py
sqlalchemy_pyodbc_mssql/tests/__init__.py
sqlalchemy_pyodbc_mssql/tests/test_dialect.py
sqlalchemy_pyodbc_mssql-0.1.1.dist-info/METADATA
sqlalchemy_pyodbc_mssql-0.1.1.dist-info/WHEEL
sqlalchemy_pyodbc_mssql-0.1.1.dist-info/entry_points.txt
sqlalchemy_pyodbc_mssql-0.1.1.dist-info/top_level.txt
sqlalchemy_pyodbc_mssql-0.1.1.dist-info/RECORD
