Metadata-Version: 2.1
Name: sqlalchemy_pyodbc_mssql
Version: 0.1.1
Summary: SA dialect for MSSQL using PyODBC which handles MSSQL-specific limitations
Home-page: https://github.com/level12/sqlalchemy_pyodbc_mssql
Author: Matt Lewellyn
Author-email: matt.lewellyn@level12.io
License: UNKNOWN
Platform: UNKNOWN
Classifier: Development Status :: 4 - Beta
Classifier: Intended Audience :: Developers
Classifier: License :: OSI Approved :: BSD License
Classifier: Operating System :: OS Independent
Classifier: Programming Language :: Python :: 3
Provides-Extra: test
